tools.py
chenliang/__init__.py
chenliang/s1.py
chenliang-1.0.0.dist-info/METADATA
chenliang-1.0.0.dist-info/WHEEL
chenliang-1.0.0.dist-info/top_level.txt
chenliang-1.0.0.dist-info/RECORD
