Metadata-Version: 2.1
Name: chenliang
Version: 1.0.0
Summary: chenchenliangliang
Home-page: UNKNOWN
Author: cl
Author-email: UNKNOWN
License: UNKNOWN
Platform: UNKNOWN
